innate/__init__.py
innate/__version__.py
innate-0.1.3.dist-info/METADATA
innate-0.1.3.dist-info/RECORD
innate-0.1.3.dist-info/WHEEL
innate-0.1.3.dist-info/top_level.txt
