Metadata-Version: 2.1
Name: innate
Version: 0.1.3
Summary: Small library for implementing command-line interfaces in Python 3.6+
Home-page: https://github.com/erm/innate/
Author: Jordan Eremieff
Author-email: jordan@eremieff.com
License: MIT License
Platform: UNKNOWN
